mdit_py_plugins/__init__.py
mdit_py_plugins/colon_fence.py
mdit_py_plugins/py.typed
mdit_py_plugins/substitution.py
mdit_py_plugins/admon/LICENSE
mdit_py_plugins/admon/__init__.py
mdit_py_plugins/admon/index.py
mdit_py_plugins/admon/port.yaml
mdit_py_plugins/amsmath/__init__.py
mdit_py_plugins/anchors/__init__.py
mdit_py_plugins/anchors/index.py
mdit_py_plugins/attrs/__init__.py
mdit_py_plugins/attrs/index.py
mdit_py_plugins/attrs/parse.py
mdit_py_plugins/container/LICENSE
mdit_py_plugins/container/README.md
mdit_py_plugins/container/__init__.py
mdit_py_plugins/container/index.py
mdit_py_plugins/container/port.yaml
mdit_py_plugins/deflist/LICENSE
mdit_py_plugins/deflist/README.md
mdit_py_plugins/deflist/__init__.py
mdit_py_plugins/deflist/index.py
mdit_py_plugins/deflist/port.yaml
mdit_py_plugins/dollarmath/__init__.py
mdit_py_plugins/dollarmath/index.py
mdit_py_plugins/field_list/__init__.py
mdit_py_plugins/footnote/LICENSE
mdit_py_plugins/footnote/__init__.py
mdit_py_plugins/footnote/index.py
mdit_py_plugins/footnote/port.yaml
mdit_py_plugins/front_matter/LICENSE
mdit_py_plugins/front_matter/__init__.py
mdit_py_plugins/front_matter/index.py
mdit_py_plugins/front_matter/port.yaml
mdit_py_plugins/myst_blocks/__init__.py
mdit_py_plugins/myst_blocks/index.py
mdit_py_plugins/myst_role/__init__.py
mdit_py_plugins/myst_role/index.py
mdit_py_plugins/tasklists/__init__.py
mdit_py_plugins/tasklists/port.yaml
mdit_py_plugins/texmath/LICENSE
mdit_py_plugins/texmath/README.md
mdit_py_plugins/texmath/__init__.py
mdit_py_plugins/texmath/index.py
mdit_py_plugins/texmath/port.yaml
mdit_py_plugins/wordcount/__init__.py
mdit_py_plugins-0.3.2.dist-info/LICENSE
mdit_py_plugins-0.3.2.dist-info/WHEEL
mdit_py_plugins-0.3.2.dist-info/METADATA
mdit_py_plugins-0.3.2.dist-info/RECORD
