Metadata-Version: 2.1
Name: mdit-py-plugins
Version: 0.3.2
Summary: Collection of plugins for markdown-it-py
Keywords: markdown,markdown-it,lexer,parser,development
Author-email: Chris Sewell <chrisj_sewell@hotmail.com>
Requires-Python: >=3.7
Classifier: Development Status :: 5 - Production/Stable
Classifier: Intended Audience :: Developers
Classifier: License :: OSI Approved :: MIT License
Classifier: Programming Language :: Python :: 3
Classifier: Programming Language :: Python :: 3.7
Classifier: Programming Language :: Python :: 3.8
Classifier: Programming Language :: Python :: 3.9
Classifier: Programming Language :: Python :: 3.10
Classifier: Programming Language :: Python :: Implementation :: CPython
Classifier: Programming Language :: Python :: Implementation :: PyPy
Classifier: Topic :: Software Development :: Libraries :: Python Modules
Classifier: Topic :: Text Processing :: Markup
Requires-Dist: markdown-it-py>=1.0.0,<3.0.0
Requires-Dist: pre-commit ; extra == "code_style"
Requires-Dist: attrs ; extra == "rtd"
Requires-Dist: myst-parser~=0.16.1 ; extra == "rtd"
Requires-Dist: sphinx-book-theme~=0.1.0 ; extra == "rtd"
Requires-Dist: coverage ; extra == "testing"
Requires-Dist: pytest ; extra == "testing"
Requires-Dist: pytest-cov ; extra == "testing"
Requires-Dist: pytest-regressions ; extra == "testing"
Project-URL: Documentation, https://markdown-it-py.readthedocs.io
Project-URL: Homepage, https://github.com/executablebooks/mdit-py-plugins
Provides-Extra: code_style
Provides-Extra: rtd
Provides-Extra: testing
